README.md
setup.cfg
setup.py
frugal/__init__.py
frugal/context.py
frugal/exceptions.py
frugal/middleware.py
frugal/processor.py
frugal/provider.py
frugal/serialize.py
frugal/subscription.py
frugal/version.py
frugal.egg-info/PKG-INFO
frugal.egg-info/SOURCES.txt
frugal.egg-info/dependency_links.txt
frugal.egg-info/requires.txt
frugal.egg-info/top_level.txt
frugal/aio/__init__.py
frugal/aio/processor.py
frugal/aio/server/__init__.py
frugal/aio/server/http_handler.py
frugal/aio/server/nats_server.py
frugal/aio/transport/__init__.py
frugal/aio/transport/async_transport.py
frugal/aio/transport/http_transport.py
frugal/aio/transport/nats_scope_transport.py
frugal/aio/transport/nats_transport.py
frugal/aio/transport/stomp_transport.py
frugal/aio/transport/transport.py
frugal/gae/__init__.py
frugal/gae/server/__init__.py
frugal/gae/server/webapp2_handler.py
frugal/gae/transport/__init__.py
frugal/gae/transport/urlfetch_transport.py
frugal/protocol/__init__.py
frugal/protocol/protocol.py
frugal/protocol/protocol_factory.py
frugal/server/__init__.py
frugal/server/http_handler.py
frugal/server/http_server.py
frugal/server/server.py
frugal/server/simple_server.py
frugal/tornado/__init__.py
frugal/tornado/processor.py
frugal/tornado/server/__init__.py
frugal/tornado/server/http_handler.py
frugal/tornado/server/nats_server.py
frugal/tornado/transport/__init__.py
frugal/tornado/transport/async_transport.py
frugal/tornado/transport/http_transport.py
frugal/tornado/transport/nats_scope_transport.py
frugal/tornado/transport/nats_transport.py
frugal/tornado/transport/transport.py
frugal/transport/__init__.py
frugal/transport/base_http_transport.py
frugal/transport/http_transport.py
frugal/transport/memory_output_buffer.py
frugal/transport/scope_transport.py
frugal/transport/transport.py
frugal/transport/transport_factory.py
frugal/util/__init__.py
frugal/util/deprecate.py
frugal/util/headers.py