Metadata-Version: 2.1
Name: frugal
Version: 2.27.1
Summary: Frugal Python Library
Home-page: http://github.com/Workiva/frugal
Maintainer: Messaging Team
Maintainer-email: messaging@workiva.com
License: UNKNOWN
Platform: UNKNOWN
Provides-Extra: tornado
Provides-Extra: gae
Provides-Extra: asyncio
